ape-gnosis/__init__.py
ape-gnosis/ecosystem.py
ape-gnosis/py.typed
ape-gnosis/version.py
ape_gnosis/__init__.py
ape_gnosis/ecosystem.py
ape_gnosis/py.typed
ape_gnosis/version.py
ape_gnosis-0.2.0.dist-info/LICENSE
ape_gnosis-0.2.0.dist-info/METADATA
ape_gnosis-0.2.0.dist-info/WHEEL
ape_gnosis-0.2.0.dist-info/top_level.txt
ape_gnosis-0.2.0.dist-info/RECORD
