Metadata-Version: 2.1
Name: ape-gnosis
Version: 0.2.0
Summary: ape-gnosis: Gnosis Ecosystem Plugin for Ape
Home-page: https://github.com/jfarid27/ape-gnosis
Author: Jalil A. Farid
Author-email: jrab227@gmail.com
License: Apache-2.0
Keywords: ethereum
Classifier: Development Status :: 4 - Beta
Classifier: Intended Audience :: Developers
Classifier: License :: OSI Approved :: Apache Software License
Classifier: Natural Language :: English
Classifier: Operating System :: MacOS
Classifier: Operating System :: POSIX
Classifier: Programming Language :: Python :: 3
Classifier: Programming Language :: Python :: 3.7
Classifier: Programming Language :: Python :: 3.8
Classifier: Programming Language :: Python :: 3.9
Classifier: Programming Language :: Python :: 3.10
Requires-Python: >=3.7,<4
License-File: LICENSE
Requires-Dist: importlib-metadata ; python_version < "3.8"
Provides-Extra: dev
Requires-Dist: pytest (<7.0,>=6.0) ; extra == 'dev'
Requires-Dist: pytest-xdist ; extra == 'dev'
Requires-Dist: pytest-cov ; extra == 'dev'
Requires-Dist: hypothesis (<7.0,>=6.2.0) ; extra == 'dev'
Requires-Dist: eth-ape (>0.6.9) ; extra == 'dev'
Requires-Dist: black (<23.0,>=22.3.0) ; extra == 'dev'
Requires-Dist: mypy (<1.0,>=0.961) ; extra == 'dev'
Requires-Dist: flake8 (<5.0,>=4.0.1) ; extra == 'dev'
Requires-Dist: isort (<6.0,>=5.10.1) ; extra == 'dev'
Requires-Dist: setuptools ; extra == 'dev'
Requires-Dist: wheel ; extra == 'dev'
Requires-Dist: twine ; extra == 'dev'
Requires-Dist: commitizen ; extra == 'dev'
Requires-Dist: pre-commit ; extra == 'dev'
Requires-Dist: pytest-watch ; extra == 'dev'
Requires-Dist: IPython ; extra == 'dev'
Requires-Dist: ipdb ; extra == 'dev'
Provides-Extra: lint
Requires-Dist: black (<23.0,>=22.3.0) ; extra == 'lint'
Requires-Dist: mypy (<1.0,>=0.961) ; extra == 'lint'
Requires-Dist: flake8 (<5.0,>=4.0.1) ; extra == 'lint'
Requires-Dist: isort (<6.0,>=5.10.1) ; extra == 'lint'
Provides-Extra: release
Requires-Dist: setuptools ; extra == 'release'
Requires-Dist: wheel ; extra == 'release'
Requires-Dist: twine ; extra == 'release'
Provides-Extra: test
Requires-Dist: pytest (<7.0,>=6.0) ; extra == 'test'
Requires-Dist: pytest-xdist ; extra == 'test'
Requires-Dist: pytest-cov ; extra == 'test'
Requires-Dist: hypothesis (<7.0,>=6.2.0) ; extra == 'test'
Requires-Dist: eth-ape (>0.6.9) ; extra == 'test'
